{"cameraMode":{"drawMode":0,"name":"Shaded","section":"Shading Mode"},"sceneLighting":true,"audioPlay":false,"sceneViewState":{"m_AlwaysRefresh":false,"showFog":true,"showSkybox":true,"showFlares":true,"showImageEffects":true,"showParticleSystems":true,"showVisualEffectGraphs":true,"m_FxEnabled":true},"in2DMode":false,"pivot":{"x":-84.50563049316406,"y":11.782759666442871,"z":-37.581016540527347},"rotation":{"x":0.09539108723402024,"y":-0.8219408392906189,"z":0.144497811794281,"w":0.5428415536880493},"size":64.87008666992188,"orthographic":false}